sparsebinarydistance/__init__.py
sparsebinarydistance/distance.py
sparsebinarydistance-0.1.dist-info/METADATA
sparsebinarydistance-0.1.dist-info/WHEEL
sparsebinarydistance-0.1.dist-info/top_level.txt
sparsebinarydistance-0.1.dist-info/RECORD
